main.py
aws_mcp_tools-0.1.1.dist-info/METADATA
aws_mcp_tools-0.1.1.dist-info/WHEEL
aws_mcp_tools-0.1.1.dist-info/top_level.txt
aws_mcp_tools-0.1.1.dist-info/RECORD
