Metadata-Version: 2.4
Name: aws-mcp-tools
Version: 0.1.1
Summary: AWS MCP tools
Requires-Python: >=3.12
Requires-Dist: fastmcp>=2.7.1
